jypypkg/__init__.py
jypypkg/jypypkg.py
jypypkg/metadata/__init__.py
jypypkg/metadata/animation_meta.py
jypypkg/metadata/audio_effect_meta.py
jypypkg/metadata/effect_meta.py
jypypkg/metadata/filter_meta.py
jypypkg/metadata/font_meta.py
jypypkg/metadata/mask_meta.py
jypypkg/metadata/transition_meta.py
jypypkg/metadata/video_effect_meta.py
tests/__init__.py
tests/test_jypypkg.py
jypypkg-0.1.2.dist-info/METADATA
jypypkg-0.1.2.dist-info/WHEEL
jypypkg-0.1.2.dist-info/top_level.txt
jypypkg-0.1.2.dist-info/RECORD
